{
  "date": "2026-07-23",
  "games": [
    {
      "calendarEventID": "14-824893-2026-07-23",
      "content": {
        "link": "/api/v1/game/824893/content"
      },
      "dayNight": "day",
      "doubleHeader": "N",
      "gameDate": "2026-07-23T16:15:00Z",
      "gameGuid": "d4256905-9c6d-4649-9da3-5470f7e1d5fc",
      "gameNumber": 1,
      "gamePk": 824893,
      "gameType": "R",
      "gamedayType": "P",
      "gamesInSeries": 4,
      "ifNecessary": "N",
      "ifNecessaryDescription": "Normal Game",
      "inningBreakLength": 120,
      "isTie": false,
      "link": "/api/v1.1/game/824893/feed/live",
      "officialDate": "2026-07-23",
      "publicFacing": true,
      "recordSource": "S",
      "reverseHomeAwayStatus": false,
      "scheduledInnings": 9,
      "season": "2026",
      "seasonDisplay": "2026",
      "seriesDescription": "Regular Season",
      "seriesGameNumber": 4,
      "status": {
        "abstractGameCode": "F",
        "abstractGameState": "Final",
        "codedGameState": "F",
        "detailedState": "Final",
        "startTimeTBD": false,
        "statusCode": "F"
      },
      "teams": {
        "away": {
          "isWinner": false,
          "leagueRecord": {
            "losses": 53,
            "pct": ".485",
            "ties": 0,
            "wins": 50
          },
          "score": 5,
          "seriesNumber": 33,
          "splitSquad": false,
          "team": {
            "id": 135,
            "link": "/api/v1/teams/135",
            "name": "San Diego Padres"
          }
        },
        "home": {
          "isWinner": true,
          "leagueRecord": {
            "losses": 42,
            "pct": ".588",
            "ties": 0,
            "wins": 60
          },
          "score": 6,
          "seriesNumber": 33,
          "splitSquad": false,
          "team": {
            "id": 144,
            "link": "/api/v1/teams/144",
            "name": "Atlanta Braves"
          }
        }
      },
      "tiebreaker": "N",
      "venue": {
        "id": 4705,
        "link": "/api/v1/venues/4705",
        "name": "Truist Park"
      }
    },
    {
      "calendarEventID": "14-824406-2026-07-23",
      "content": {
        "link": "/api/v1/game/824406/content"
      },
      "dayNight": "day",
      "doubleHeader": "N",
      "gameDate": "2026-07-23T17:10:00Z",
      "gameGuid": "a7117f74-208c-4e4c-8292-c036c279e7af",
      "gameNumber": 1,
      "gamePk": 824406,
      "gameType": "R",
      "gamedayType": "P",
      "gamesInSeries": 4,
      "ifNecessary": "N",
      "ifNecessaryDescription": "Normal Game",
      "inningBreakLength": 120,
      "isTie": false,
      "link": "/api/v1.1/game/824406/feed/live",
      "officialDate": "2026-07-23",
      "publicFacing": true,
      "recordSource": "S",
      "reverseHomeAwayStatus": false,
      "scheduledInnings": 9,
      "season": "2026",
      "seasonDisplay": "2026",
      "seriesDescription": "Regular Season",
      "seriesGameNumber": 4,
      "status": {
        "abstractGameCode": "F",
        "abstractGameState": "Final",
        "codedGameState": "F",
        "detailedState": "Final",
        "startTimeTBD": false,
        "statusCode": "F"
      },
      "teams": {
        "away": {
          "isWinner": true,
          "leagueRecord": {
            "losses": 53,
            "pct": ".490",
            "ties": 0,
            "wins": 51
          },
          "score": 3,
          "seriesNumber": 33,
          "splitSquad": false,
          "team": {
            "id": 142,
            "link": "/api/v1/teams/142",
            "name": "Minnesota Twins"
          }
        },
        "home": {
          "isWinner": false,
          "leagueRecord": {
            "losses": 50,
            "pct": ".519",
            "ties": 0,
            "wins": 54
          },
          "score": 1,
          "seriesNumber": 33,
          "splitSquad": false,
          "team": {
            "id": 114,
            "link": "/api/v1/teams/114",
            "name": "Cleveland Guardians"
          }
        }
      },
      "tiebreaker": "N",
      "venue": {
        "id": 5,
        "link": "/api/v1/venues/5",
        "name": "Progressive Field"
      }
    },
    {
      "calendarEventID": "14-822785-2026-07-23",
      "content": {
        "link": "/api/v1/game/822785/content"
      },
      "dayNight": "day",
      "doubleHeader": "N",
      "gameDate": "2026-07-23T19:07:00Z",
      "gameGuid": "a6535a10-7645-43f0-bc29-1a4049d9cf5f",
      "gameNumber": 1,
      "gamePk": 822785,
      "gameType": "R",
      "gamedayType": "P",
      "gamesInSeries": 4,
      "ifNecessary": "N",
      "ifNecessaryDescription": "Normal Game",
      "inningBreakLength": 120,
      "isTie": false,
      "link": "/api/v1.1/game/822785/feed/live",
      "officialDate": "2026-07-23",
      "publicFacing": true,
      "recordSource": "S",
      "reverseHomeAwayStatus": false,
      "scheduledInnings": 9,
      "season": "2026",
      "seasonDisplay": "2026",
      "seriesDescription": "Regular Season",
      "seriesGameNumber": 4,
      "status": {
        "abstractGameCode": "F",
        "abstractGameState": "Final",
        "codedGameState": "O",
        "detailedState": "Game Over",
        "startTimeTBD": false,
        "statusCode": "O"
      },
      "teams": {
        "away": {
          "isWinner": false,
          "leagueRecord": {
            "losses": 43,
            "pct": ".578",
            "ties": 0,
            "wins": 59
          },
          "score": 1,
          "seriesNumber": 33,
          "splitSquad": false,
          "team": {
            "id": 139,
            "link": "/api/v1/teams/139",
            "name": "Tampa Bay Rays"
          }
        },
        "home": {
          "isWinner": true,
          "leagueRecord": {
            "losses": 56,
            "pct": ".456",
            "ties": 0,
            "wins": 47
          },
          "score": 3,
          "seriesNumber": 33,
          "splitSquad": false,
          "team": {
            "id": 141,
            "link": "/api/v1/teams/141",
            "name": "Toronto Blue Jays"
          }
        }
      },
      "tiebreaker": "N",
      "venue": {
        "id": 14,
        "link": "/api/v1/venues/14",
        "name": "Rogers Centre"
      }
    },
    {
      "calendarEventID": "14-823042-2026-07-23",
      "content": {
        "link": "/api/v1/game/823042/content"
      },
      "dayNight": "day",
      "description": "Makeup of 6/25 PPD",
      "doubleHeader": "N",
      "gameDate": "2026-07-23T21:15:00Z",
      "gameGuid": "aac8d70c-d01e-457d-95f0-b925476a0514",
      "gameNumber": 1,
      "gamePk": 823042,
      "gameType": "R",
      "gamedayType": "P",
      "gamesInSeries": 1,
      "ifNecessary": "N",
      "ifNecessaryDescription": "Normal Game",
      "inningBreakLength": 120,
      "link": "/api/v1.1/game/823042/feed/live",
      "officialDate": "2026-07-23",
      "publicFacing": true,
      "recordSource": "S",
      "rescheduledFrom": "2026-06-25T23:45:00Z",
      "rescheduledFromDate": "2026-06-25",
      "reverseHomeAwayStatus": false,
      "scheduledInnings": 9,
      "season": "2026",
      "seasonDisplay": "2026",
      "seriesDescription": "Regular Season",
      "seriesGameNumber": 1,
      "status": {
        "abstractGameCode": "L",
        "abstractGameState": "Live",
        "codedGameState": "I",
        "detailedState": "In Progress",
        "startTimeTBD": false,
        "statusCode": "I"
      },
      "teams": {
        "away": {
          "leagueRecord": {
            "losses": 49,
            "pct": ".520",
            "ties": 0,
            "wins": 53
          },
          "score": 0,
          "seriesNumber": 34,
          "splitSquad": false,
          "team": {
            "id": 109,
            "link": "/api/v1/teams/109",
            "name": "Arizona Diamondbacks"
          }
        },
        "home": {
          "leagueRecord": {
            "losses": 49,
            "pct": ".515",
            "ties": 0,
            "wins": 52
          },
          "score": 0,
          "seriesNumber": 34,
          "splitSquad": false,
          "team": {
            "id": 138,
            "link": "/api/v1/teams/138",
            "name": "St. Louis Cardinals"
          }
        }
      },
      "tiebreaker": "N",
      "venue": {
        "id": 2889,
        "link": "/api/v1/venues/2889",
        "name": "Busch Stadium"
      }
    },
    {
      "calendarEventID": "14-824247-2026-07-23",
      "content": {
        "link": "/api/v1/game/824247/content"
      },
      "dayNight": "night",
      "doubleHeader": "N",
      "gameDate": "2026-07-23T22:40:00Z",
      "gameGuid": "dcb0b28f-63b6-476d-ba41-c28b873c3773",
      "gameNumber": 1,
      "gamePk": 824247,
      "gameType": "R",
      "gamedayType": "P",
      "gamesInSeries": 4,
      "ifNecessary": "N",
      "ifNecessaryDescription": "Normal Game",
      "inningBreakLength": 145,
      "link": "/api/v1.1/game/824247/feed/live",
      "officialDate": "2026-07-23",
      "publicFacing": true,
      "recordSource": "S",
      "reverseHomeAwayStatus": false,
      "scheduledInnings": 9,
      "season": "2026",
      "seasonDisplay": "2026",
      "seriesDescription": "Regular Season",
      "seriesGameNumber": 1,
      "status": {
        "abstractGameCode": "P",
        "abstractGameState": "Preview",
        "codedGameState": "P",
        "detailedState": "Pre-Game",
        "startTimeTBD": false,
        "statusCode": "P"
      },
      "teams": {
        "away": {
          "leagueRecord": {
            "losses": 60,
            "pct": ".417",
            "ties": 0,
            "wins": 43
          },
          "score": 0,
          "seriesNumber": 34,
          "splitSquad": false,
          "team": {
            "id": 118,
            "link": "/api/v1/teams/118",
            "name": "Kansas City Royals"
          }
        },
        "home": {
          "leagueRecord": {
            "losses": 54,
            "pct": ".471",
            "ties": 0,
            "wins": 48
          },
          "score": 0,
          "seriesNumber": 34,
          "splitSquad": false,
          "team": {
            "id": 116,
            "link": "/api/v1/teams/116",
            "name": "Detroit Tigers"
          }
        }
      },
      "tiebreaker": "N",
      "venue": {
        "id": 2394,
        "link": "/api/v1/venues/2394",
        "name": "Comerica Park"
      }
    }
  ],
  "observedAt": "2026-07-23T21:23:56.566304Z",
  "parity": [
    {
      "askSum": 1.0099999999999998,
      "event": "KXMLBGAME-26JUL231840KCDET",
      "grossEdge": -0.009999999999999787,
      "netEdge": -0.029999999999999787,
      "outcomes": [
        {
          "ask": {
            "price": 0.32999999999999996,
            "size": 751023.42
          },
          "bid": {
            "price": 0.32,
            "size": 225749.61
          },
          "name": "Kansas City",
          "ticker": "KXMLBGAME-26JUL231840KCDET-KC",
          "volume": 166173.25
        },
        {
          "ask": {
            "price": 0.6799999999999999,
            "size": 697707.61
          },
          "bid": {
            "price": 0.67,
            "size": 144351.07
          },
          "name": "Detroit",
          "ticker": "KXMLBGAME-26JUL231840KCDET-DET",
          "volume": 315481.86
        }
      ],
      "signal": "NO TRADE",
      "status": "active",
      "title": "Kansas City vs Detroit"
    },
    {
      "askSum": 1.0100000000000002,
      "event": "KXMLBGAME-26JUL231715AZSTL",
      "grossEdge": -0.010000000000000231,
      "netEdge": -0.03000000000000023,
      "outcomes": [
        {
          "ask": {
            "price": 0.43000000000000005,
            "size": 269752.7
          },
          "bid": {
            "price": 0.42,
            "size": 6221.7
          },
          "name": "Arizona",
          "ticker": "KXMLBGAME-26JUL231715AZSTL-AZ",
          "volume": 1001724.63
        },
        {
          "ask": {
            "price": 0.5800000000000001,
            "size": 16561.95
          },
          "bid": {
            "price": 0.57,
            "size": 71845.56
          },
          "name": "St. Louis",
          "ticker": "KXMLBGAME-26JUL231715AZSTL-STL",
          "volume": 1106872.03
        }
      ],
      "signal": "NO TRADE",
      "status": "active",
      "title": "Arizona vs St. Louis"
    }
  ],
  "schemaVersion": 1,
  "sourceHealth": {
    "kalshiOpenEvents": 46,
    "kalshiStatus": 200,
    "kalshiTodayMarkets": 4,
    "marketObservedAt": "2026-07-23T21:23:56.566304Z",
    "mlbStatus": 200,
    "relay": "github-actions",
    "usingSnapshot": false
  }
}
